phasme/__init__.py
phasme/__main__.py
phasme/asp.py
phasme/build_graph.py
phasme/cli.py
phasme/commons.py
phasme/extract_links.py
phasme/graph_to_tex.py
phasme/graphics.py
phasme/info.py
phasme/routines.py
phasme-0.0.16.dist-info/METADATA
phasme-0.0.16.dist-info/WHEEL
phasme-0.0.16.dist-info/entry_points.txt
phasme-0.0.16.dist-info/top_level.txt
phasme-0.0.16.dist-info/RECORD
